uuidtoimage/__init__.py
uuidtoimage/generate.py
uuidtoimage/run.py
uuidtoimage-0.0.1.dist-info/LICENSE
uuidtoimage-0.0.1.dist-info/METADATA
uuidtoimage-0.0.1.dist-info/WHEEL
uuidtoimage-0.0.1.dist-info/RECORD
