Metadata-Version: 2.1
Name: uuidtoimage
Version: 0.0.1
Summary: Convert a uuid to an image
Author: Nate Schultz
Author-email: nate.schultz@outlook.com
Classifier: Programming Language :: Python :: 2
Classifier: Programming Language :: Python :: 2.7
Classifier: Programming Language :: Python :: 3
Classifier: Programming Language :: Python :: 3.4
Classifier: Programming Language :: Python :: 3.5
Classifier: Programming Language :: Python :: 3.6
Classifier: Programming Language :: Python :: 3.7
Classifier: Programming Language :: Python :: 3.8
Classifier: Programming Language :: Python :: 3.9
Classifier: Programming Language :: Python :: 3.10
Classifier: Programming Language :: Python :: 3.11
Requires-Dist: imageio (==2.31.1)
Requires-Dist: numpy (==1.24.2)
